nnkortex/__init__.py
nnkortex-0.0.0.dist-info/METADATA
nnkortex-0.0.0.dist-info/WHEEL
nnkortex-0.0.0.dist-info/top_level.txt
nnkortex-0.0.0.dist-info/RECORD
