Metadata-Version: 2.1
Name: nnkortex
Version: 0.0.0
Summary: Core for Neural Networks
Home-page: UNKNOWN
Author: Edgar Y. Walker
Author-email: edgar.y.walker@mnf.uni-tuebingen.de
License: UNKNOWN
Platform: UNKNOWN
